koala_buckets/__init__.py
koala_buckets/koala_gcs/__init__.py
koala_buckets/koala_gcs/gcs_bucket.py
koala_buckets/koala_onprem_s3/__init__.py
koala_buckets/koala_onprem_s3/s3_bucket.py
koala_buckets-0.0.2.dist-info/METADATA
koala_buckets-0.0.2.dist-info/WHEEL
koala_buckets-0.0.2.dist-info/top_level.txt
koala_buckets-0.0.2.dist-info/RECORD
